[{"cuisine": "Meksika, Pub", "rank": "1", "location": "\u00c7ayyolu, Ankara", "restaurant_name": "Pool Pub", "rating": "3.3"}, {"cuisine": "Karadeniz", "rank": "2", "location": "\u00c7ayyolu, Ankara", "restaurant_name": "Hev Zigana", "rating": "3.4"}, {"cuisine": "Meyhane", "rank": "3", "location": "Kavakl\u0131dere, Ankara", "restaurant_name": "Ta\u00e7o Meyhane", "rating": "3.2"}, {"cuisine": "Balik, Deniz   r  nleri", "rank": "4", "location": "Gazi Osman Pa\u015fa, Ankara", "restaurant_name": "Yelken Bal\u0131k Seyfi", "rating": "3.8"}, {"cuisine": "Fast Food, T  rk", "rank": "5", "location": "S\u0131hhiye, Ankara", "restaurant_name": "Morgi", "rating": "3.1"}, {"cuisine": "Steakhouse   Et lokantas  ,   ", "rank": "6", "location": "S\u00f6\u011f\u00fct\u00f6z\u00fc, Ankara", "restaurant_name": "Vesperna", "rating": "3.9"}, {"cuisine": "Kebap, Pide, T  rk", "rank": "7", "location": "K\u00fc\u00e7\u00fck Esat, Ankara", "restaurant_name": "K\u0131rlang\u0131\u00e7 Etli Ekmek", "rating": "3.1"}, {"cuisine": "Meyhane", "rank": "8", "location": "Gazi Osman Pa\u015fa, Ankara", "restaurant_name": "Miso Meyhane", "rating": "3.1"}, {"cuisine": "Balik, Deniz   r  nleri", "rank": "9", "location": "Gazi Osman Pa\u015fa, Ankara", "restaurant_name": "Trilye", "rating": "4.6"}, {"cuisine": "T  rk", "rank": "10", "location": "K\u0131z\u0131lay, Ankara", "restaurant_name": "\u00dcz\u00fcm Cafe &amp; Restaurant - First Apar...", "rating": "3.0"}, {"cuisine": "D  nya Mutfa    ", "rank": "11", "location": "Kavakl\u0131dere, Ankara", "restaurant_name": "Hayyami \u015earap Evi", "rating": "3.3"}, {"cuisine": "Karadeniz, T  rk", "rank": "12", "location": "K\u0131z\u0131lay, Ankara", "restaurant_name": "Lazut Cafe", "rating": "3.0"}, {"cuisine": "Pub", "rank": "13", "location": "Gazi Osman Pa\u015fa, Ankara", "restaurant_name": "Q&#039;ba Bar", "rating": "3.0"}, {"cuisine": "Balik, Deniz   r  nleri,   ", "rank": "14", "location": "Gazi Osman Pa\u015fa, Ankara", "restaurant_name": "Fige Restaurant", "rating": "3.7"}, {"cuisine": "Pub", "rank": "15", "location": "K\u0131z\u0131lay, Ankara", "restaurant_name": "Return Cafe &amp; Pub", "rating": "-"}, {"cuisine": "T  rk", "rank": "16", "location": "K\u0131z\u0131lay, Ankara", "restaurant_name": "Kanat\u00e7\u0131", "rating": "3.0"}, {"cuisine": "Balik, Deniz   r  nleri", "rank": "17", "location": "Bat\u0131kent, Ankara", "restaurant_name": "Norve\u00e7 Bal\u0131k Evi", "rating": "3.1"}, {"cuisine": "Kebap, T  rk", "rank": "18", "location": "Balgat, Ankara", "restaurant_name": "Masaba\u015f\u0131", "rating": "3.1"}, {"cuisine": "Pub, D  nya Mutfa    ", "rank": "19", "location": "Bah\u00e7elievler, Ankara", "restaurant_name": "\u015eantiye Pub", "rating": "3.0"}, {"cuisine": "Meyhane, Ege, Akdeniz", "rank": "20", "location": "Kavakl\u0131dere, Ankara", "restaurant_name": "Farabi Kom\u015fu", "rating": "3.3"}, {"cuisine": "Ev Yeme  i", "rank": "21", "location": "K\u0131z\u0131lay, Ankara", "restaurant_name": "\u015eaziyem Ev Yemekleri", "rating": "3.1"}, {"cuisine": "Fast Food, T  rk", "rank": "22", "location": "Demetevler, Ankara", "restaurant_name": "Sudem Tantuni &amp; Cafe", "rating": "3.4"}, {"cuisine": "Meyhane, T  rk", "rank": "23", "location": "Gazi Osman Pa\u015fa, Ankara", "restaurant_name": "Me\u015frep \u00c7ankaya", "rating": "3.5"}, {"cuisine": "Cafe, Meksika, D  nya   ", "rank": "24", "location": "K\u0131z\u0131lay, Ankara", "restaurant_name": "Koliba Cafe", "rating": "-"}, {"cuisine": "Ev Yeme  i, T  rk", "rank": "25", "location": "K\u0131z\u0131lay, Ankara", "restaurant_name": "Erguvan Kap\u0131s\u0131", "rating": "-"}]
